{
  "TalkAgentResponse": {
    "@SCI": "@5c3216df-8a3c-2f43-6cc3-1cdb9a32eac2@c302f0a6-7d1b-4355-85e8-3f41ef23c4dd",
    "@IID": "3ff2e5fc-0980-4b62-8a56-4b7c311642ae",
    "@TimeStamp": "2018-02-02T06:13:13.5587651Z",
    "@ResponseCode": "Found",
    "@Version": "6",
    "Display": {
      "OutText": {
        "#text": "Perfect. How many American Airlines Aadvantage miles would you like to transfer to your Neptune Airline points program?"
      },
      "AlternateOutText": {
        "#text": "Perfect. How many American Airlines AAdvantage miles would you like to transfer to your Neptune Airline points program?"
      },
      "AlternateOutText2": {
        "#text": "Perfect. How many American Airlines AAdvantage miles would you like to transfer to your Neptune Airline points program?"
      }
    },
    "TimeOut": 300,
    "sessionBootstrap": {
      "moduleState": {
        "Brain": "197097a4-8fda-4df0-aa28-be5baaedfa93"
      },
      "conceptCaptures": {
        "agent": {},
        "intent": {},
        "node": {
          "580a9231-3042-4d36-b0f1-b2e97a72b761": {
            "AIRLINES": {
              "value": "American Airlines",
              "literal": "American Airlines"
            }
          }
        },
        "correction": null
      }
    },
    "activeIntent": "4862134332995817338",
    "conceptsInFocus": [
      "ENTER_MILES"
    ]
  }
}